Metadata-Version: 1.1
Name: livingbio-django-q
Version: 0.8.1
Summary: A multiprocessing distributed task queue for Django
Home-page: https://django-q.readthedocs.org
Author: Ilan Steemers
Author-email: koed0@gmail.com
License: MIT
Keywords: django distributed task queue worker scheduler cron redis disque ironmq sqs orm mongodb multiprocessing rollbar
Platform: UNKNOWN
Classifier: Development Status :: 4 - Beta
Classifier: Environment :: Web Environment
Classifier: Framework :: Django
Classifier: Intended Audience :: Developers
Classifier: License :: OSI Approved :: MIT License
Classifier: Operating System :: POSIX
Classifier: Operating System :: MacOS
Classifier: Programming Language :: Python
Classifier: Programming Language :: Python :: 2
Classifier: Programming Language :: Python :: 2.7
Classifier: Programming Language :: Python :: 3
Classifier: Programming Language :: Python :: 3.4
Classifier: Programming Language :: Python :: 3.5
Classifier: Programming Language :: Python :: 3.6
Classifier: Topic :: Internet :: WWW/HTTP
Classifier: Topic :: Software Development :: Libraries :: Python Modules
